Metadata-Version: 1.0
Name: dsnd-probability-14072020
Version: 0.2
Summary: Gaussian and Binomial distributions
Home-page: UNKNOWN
Author: Ishwarya Chandramouli
Author-email: UNKNOWN
License: UNKNOWN
Platform: UNKNOWN
